{
  "cliente": "Cezinha de Madureira",
  "atualizado_em": "2026-06-29T16:17:35-03:00",
  "fonte": "Meta Marketing API + Graph API",
  "contas": {
    "ad_account": "act_1395564544098811",
    "fb_page_id": "1401978510018003",
    "ig_id": "17841400472685855",
    "ig_username": "cezinhademadureira"
  },
  "seguidores": {
    "fb_atual": 106725,
    "ig_atual": 191715,
    "ig_posts": 445,
    "serie": [
      {
        "data": "2026-06-17",
        "fb": 106722,
        "ig": 191464
      },
      {
        "data": "2026-06-18",
        "fb": 106718,
        "ig": 191477
      },
      {
        "data": "2026-06-19",
        "fb": 106710,
        "ig": 191425
      },
      {
        "data": "2026-06-20",
        "fb": 106702,
        "ig": 191478
      },
      {
        "data": "2026-06-21",
        "fb": 106699,
        "ig": 191478
      },
      {
        "data": "2026-06-22",
        "fb": 106695,
        "ig": 191502
      },
      {
        "data": "2026-06-23",
        "fb": 106694,
        "ig": 191518
      },
      {
        "data": "2026-06-24",
        "fb": 106698,
        "ig": 191577
      },
      {
        "data": "2026-06-25",
        "fb": 106703,
        "ig": 191659
      },
      {
        "data": "2026-06-26",
        "fb": 106704,
        "ig": 191598
      },
      {
        "data": "2026-06-27",
        "fb": 106717,
        "ig": 191676
      },
      {
        "data": "2026-06-28",
        "fb": 106718,
        "ig": 191703
      },
      {
        "data": "2026-06-29",
        "fb": 106725,
        "ig": 191715
      }
    ],
    "ig_follows": 4201
  },
  "publico": {
    "atualizado_em": "2026-06-29T16:17:35-03:00",
    "timeframe": "last_30_days",
    "seguidores": {
      "genero": [
        {
          "k": "U",
          "v": 76641
        },
        {
          "k": "M",
          "v": 42217
        },
        {
          "k": "F",
          "v": 37613
        }
      ],
      "idade": [
        {
          "k": "35-44",
          "v": 44336
        },
        {
          "k": "25-34",
          "v": 37443
        },
        {
          "k": "45-54",
          "v": 35694
        },
        {
          "k": "18-24",
          "v": 20174
        },
        {
          "k": "55-64",
          "v": 13150
        },
        {
          "k": "65+",
          "v": 3711
        },
        {
          "k": "13-17",
          "v": 1963
        }
      ],
      "cidades": [
        {
          "k": "São Paulo, São Paulo (state)",
          "v": 15201
        },
        {
          "k": "Rio de Janeiro, Rio de Janeiro (state)",
          "v": 2359
        },
        {
          "k": "Guarulhos, São Paulo (state)",
          "v": 1586
        },
        {
          "k": "Saint Petersburg, Saint Petersburg",
          "v": 1228
        },
        {
          "k": "Campinas, São Paulo (state)",
          "v": 1035
        },
        {
          "k": "New York, New York",
          "v": 887
        },
        {
          "k": "Goiânia, Goiás",
          "v": 878
        },
        {
          "k": "Belo Horizonte, Minas Gerais",
          "v": 848
        },
        {
          "k": "Delhi, Delhi",
          "v": 815
        },
        {
          "k": "Osasco, São Paulo (state)",
          "v": 814
        },
        {
          "k": "Salvador, Bahia",
          "v": 800
        },
        {
          "k": "Piracicaba, São Paulo (state)",
          "v": 782
        }
      ]
    },
    "engajados": {
      "genero": [
        {
          "k": "M",
          "v": 2467
        },
        {
          "k": "F",
          "v": 2124
        },
        {
          "k": "U",
          "v": 760
        }
      ],
      "cidades": [
        {
          "k": "São Paulo, São Paulo (state)",
          "v": 1498
        },
        {
          "k": "Guarulhos, São Paulo (state)",
          "v": 248
        },
        {
          "k": "Mauá, São Paulo (state)",
          "v": 143
        },
        {
          "k": "Osasco, São Paulo (state)",
          "v": 131
        },
        {
          "k": "Barueri, São Paulo (state)",
          "v": 129
        },
        {
          "k": "Campinas, São Paulo (state)",
          "v": 77
        },
        {
          "k": "Santo André, São Paulo (state)",
          "v": 71
        },
        {
          "k": "São Bernardo do Campo, São Paulo (state)",
          "v": 69
        },
        {
          "k": "São José dos Campos, São Paulo (state)",
          "v": 63
        },
        {
          "k": "Piracicaba, São Paulo (state)",
          "v": 62
        },
        {
          "k": "Carapicuíba, São Paulo (state)",
          "v": 60
        },
        {
          "k": "Praia Grande, São Paulo (state)",
          "v": 44
        }
      ]
    },
    "alcance_30d": 822335,
    "views_30d": 1425509,
    "top_posts": [
      {
        "permalink": "https://www.instagram.com/reel/DaA5L_ZJoLl/",
        "thumb": "https://scontent-iad3-1.cdninstagram.com/v/t51.82787-15/728704269_18592178986015757_6660342566854278600_n.jpg?stp=dst-jpg_e35_tt6&_nc_cat=108&ccb=7-5&_nc_sid=18de74&efg=eyJlZmdfdGFnIjoiQ0xJUFMuYmVzdF9pbWFnZV91cmxnZW4uQzMifQ%3D%3D&_nc_eui2=AeFfvfi7i3-d1xVKwiqYDQmHGRF-CpXZxFUZEX4KldnEVb1_l5LcgrOGTQ5nFEhLu47iYSgQyTDcWcUoNZSFTcZn&_nc_ohc=_fZ2X4BYbkwQ7kNvwGRGywB&_nc_oc=AdrJSibggqLEneueX-vapAPz4t_ESNCtuDUrHlR9q77jxxA9HdhgkKPCCSKgafm0NGc&_nc_zt=23&_nc_ht=scontent-iad3-1.cdninstagram.com&edm=AM6HXa8EAAAA&_nc_gid=ML2M_EBJIloVzb1Fi8sz-A&_nc_tpa=Q5bMBQH92z0F530x_zvfJ5NTUJPG7BAHOof_gEU2sqzKtkyE-0cU0P1tViNEReznJ4wWJGzg0B8L-yF3dw&oh=00_Af9gnV2_Gmth41TkTQ4s1HTvKPAxDPG4YEfR6AaSyQ7olQ&oe=6A48A711",
        "data": "2026-06-25",
        "tipo": "Reel",
        "likes": 254,
        "comentarios": 66,
        "reach": 4196,
        "shares": 95,
        "saved": 4,
        "interacoes": 446,
        "legenda": "A nossa história é construída pelas pessoas que encontramos ao longo do caminho.  Cada conversa, cada encontro e cada hi"
      },
      {
        "permalink": "https://www.instagram.com/reel/DaBD31ehDE3/",
        "thumb": "https://scontent-iad3-1.cdninstagram.com/v/t51.82787-15/730083477_18592202194015757_5330050751880061701_n.jpg?stp=dst-jpg_e35_tt6&_nc_cat=101&ccb=7-5&_nc_sid=18de74&efg=eyJlZmdfdGFnIjoiQ0xJUFMuYmVzdF9pbWFnZV91cmxnZW4uQzMifQ%3D%3D&_nc_eui2=AeEzp_MRRKefbKbZdFYhiqvV4Wku9YdHevrhaS71h0d6-k1_kafcvcEdISVcA6bPXZ4nQiW7zrhgjbJrxk3EsWr_&_nc_ohc=fhjVxWtwSVAQ7kNvwF8XXgH&_nc_oc=AdpWI4Y7RQx7wucQkeDuobxfHsQ5m2DAUw_14En2Ghe-AtzLCIfn-lrvnhzgP6_5Ae4&_nc_zt=23&_nc_ht=scontent-iad3-1.cdninstagram.com&edm=AM6HXa8EAAAA&_nc_gid=ML2M_EBJIloVzb1Fi8sz-A&_nc_tpa=Q5bMBQHRS1jSrYY4n20ASWXhQe7jiv3kxXME_VRVGUGovlBj5ioqgAxrM1kQsO711-LNrF8pMtvzLKMjWA&oh=00_Af84HqVs1dCdoOlxXOYPWzLYTwWB-d-Ehvq9kCFwws9FeQ&oe=6A4887D4",
        "data": "2026-06-25",
        "tipo": "Reel",
        "likes": 189,
        "comentarios": 48,
        "reach": 1943,
        "shares": 10,
        "saved": 5,
        "interacoes": 279,
        "legenda": "“Esperei com paciência no Senhor, e Ele se inclinou para mim e ouviu o meu clamor.” – Salmo 40:1  Davi nos ensina que es"
      },
      {
        "permalink": "https://www.instagram.com/reel/DaDwaUipE5B/",
        "thumb": "https://scontent-iad6-1.cdninstagram.com/v/t51.82787-15/728855231_18592541275015757_919401160892933468_n.jpg?stp=dst-jpg_e35_tt6&_nc_cat=107&ccb=7-5&_nc_sid=18de74&efg=eyJlZmdfdGFnIjoiQ0xJUFMuYmVzdF9pbWFnZV91cmxnZW4uQzMifQ%3D%3D&_nc_eui2=AeHTm5uu-_9Iw2x95BMOhdsq-4K2k3SN1VX7graTdI3VVe-E5XUrmBGWQ1jaBtI_Sb2W8DjvwILIHcqDKxrk9-qz&_nc_ohc=UCfUftpUIBwQ7kNvwFKoajd&_nc_oc=AdrwgvyLNL-1BwTXT50jfUV5cDN4w7ZCJ2iW0148FzCwSr8DmdgfcJtCHNCXYjG2Rrg&_nc_zt=23&_nc_ht=scontent-iad6-1.cdninstagram.com&edm=AM6HXa8EAAAA&_nc_gid=ML2M_EBJIloVzb1Fi8sz-A&_nc_tpa=Q5bMBQEak-Lj5_8e7x5JZGNF8nuQsVk5T5XBZSf0sVZpLh_Z15ORdjauFvCpdbtt4_unm3-9QKft3DbJzw&oh=00_Af8BQBEPD3_NpgmRbWWHdy-anEpzviiM8zZflTx9uujC3g&oe=6A48810D",
        "data": "2026-06-26",
        "tipo": "Reel",
        "likes": 161,
        "comentarios": 52,
        "reach": 2204,
        "shares": 39,
        "saved": 3,
        "interacoes": 273,
        "legenda": "Quem já precisou de atendimento médico sabe que a espera não é apenas um incômodo.  Ela gera preocupação, ansiedade e, m"
      },
      {
        "permalink": "https://www.instagram.com/p/DZ-xiQ3pRWO/",
        "thumb": "https://scontent-iad3-2.cdninstagram.com/v/t51.82787-15/728474279_18591935473015757_4939478781910995182_n.jpg?stp=dst-jpg_e35_tt6&_nc_cat=103&ccb=7-5&_nc_sid=18de74&efg=eyJlZmdfdGFnIjoiRkVFRC5iZXN0X2ltYWdlX3VybGdlbi5DMyJ9&_nc_eui2=AeGEc2oKL3ND-mSpbqsyn1OnYcu3t7YPnqFhy7e3tg-eoQRvEn_Vn0SsBO4Yn8-s2pyu1ZfVv7G26wKA_Dt0Fy1w&_nc_ohc=5PkJjBBoTgcQ7kNvwHFaQZQ&_nc_oc=Ado6afN8QdXSCdmXRdgV-kbuwoGAadMLFpwJjmU6mq4XnOAgwTpRhfDS037jWLRehWI&_nc_zt=23&_nc_ht=scontent-iad3-2.cdninstagram.com&edm=AM6HXa8EAAAA&_nc_gid=ML2M_EBJIloVzb1Fi8sz-A&oh=00_Af9DpcqvJS6csPDpMKZ2J7NFzp828whd-jUbGPsav70HXw&oe=6A487F6B",
        "data": "2026-06-24",
        "tipo": "Foto",
        "likes": 174,
        "comentarios": 15,
        "reach": 5625,
        "shares": 3,
        "saved": 1,
        "interacoes": 203,
        "legenda": "Juntos somos fortes"
      },
      {
        "permalink": "https://www.instagram.com/p/DZ8p1YbiSv0/",
        "thumb": "https://scontent-iad6-1.cdninstagram.com/v/t51.82787-15/726849399_18591686029015757_2173389523377270542_n.jpg?stp=dst-jpg_e35_tt6&_nc_cat=100&ccb=7-5&_nc_sid=18de74&efg=eyJlZmdfdGFnIjoiQ0FST1VTRUxfSVRFTS5iZXN0X2ltYWdlX3VybGdlbi5DMyJ9&_nc_eui2=AeGfjcB2vMSR5OXEMLf4vcU34cxVy_Tf8QbhzFXL9N_xBlxXuYpaicZiK0ri7pU0_1sT1l2fvKd14kegmnE7cfLP&_nc_ohc=1PmJ50xt7TMQ7kNvwG_alR1&_nc_oc=AdoSN_itTOjSF6sN4ajPraYsaYO125ZT5tZOKMlvpTFWNxusNjSB5q1SrNzvfG-kIGw&_nc_zt=23&_nc_ht=scontent-iad6-1.cdninstagram.com&edm=AM6HXa8EAAAA&_nc_gid=ML2M_EBJIloVzb1Fi8sz-A&oh=00_Af87ziQSr17KRGaDvrp6Xrm4WNKaH9mNl9paKlRc6QqEJQ&oe=6A4883F8",
        "data": "2026-06-23",
        "tipo": "Carrossel",
        "likes": 136,
        "comentarios": 28,
        "reach": 1366,
        "shares": 7,
        "saved": 1,
        "interacoes": 187,
        "legenda": "Quem empreende sabe que gerar empregos, manter um negócio funcionando e continuar acreditando no Brasil não é tarefa sim"
      },
      {
        "permalink": "https://www.instagram.com/reel/DZ-j1e9pVxC/",
        "thumb": "https://scontent-iad3-2.cdninstagram.com/v/t51.82787-15/728731068_18591906160015757_735390114221906547_n.jpg?stp=dst-jpg_e35_tt6&_nc_cat=103&ccb=7-5&_nc_sid=18de74&efg=eyJlZmdfdGFnIjoiQ0xJUFMuYmVzdF9pbWFnZV91cmxnZW4uQzMifQ%3D%3D&_nc_eui2=AeElqOjwWE0adiU_hfC_0M-3ezU8ZHIAsmx7NTxkcgCybNI4QVLj9Iy_Rlk9RSX7k4JSOz-7hzq7gTK9x67ONcnr&_nc_ohc=IpJNbIrIfQMQ7kNvwH_GCwq&_nc_oc=Adobvdo8o6M5OVArS35RS118lqOKJB7YJZyI-CUYDzRfuvV4lpoKMI169sVf4-xfV7E&_nc_zt=23&_nc_ht=scontent-iad3-2.cdninstagram.com&edm=AM6HXa8EAAAA&_nc_gid=ML2M_EBJIloVzb1Fi8sz-A&_nc_tpa=Q5bMBQHPwjawLNgspr2BoEsUOtccG8Wn9WyPH7KRBii5EwfrzOYez677ChhLZARyFdnvaJfP3D-V8TEuxg&oh=00_Af93fYHeO0Xjd3w1jrlZ3ykeQBcGg4DbZ4dN54TmPR2NAA&oe=6A4881E6",
        "data": "2026-06-24",
        "tipo": "Reel",
        "likes": 115,
        "comentarios": 27,
        "reach": 2011,
        "shares": 4,
        "saved": 3,
        "interacoes": 163,
        "legenda": "Ontem foi uma daquelas noites que renovam a nossa confiança nas pessoas. 🙌  Ao lado do amigo Lika Gutierrez, tive a opor"
      }
    ]
  },
  "consolidado": {
    "totais": {
      "impressions": 1657936,
      "reach": 1047528,
      "clicks": 22583,
      "link_clicks": 16773,
      "engajamentos": 160314,
      "reacoes": 6885,
      "comentarios": 190,
      "salvamentos": 45,
      "compartilhamentos": 144,
      "video_plays": 973332,
      "video_views": 136277,
      "thruplays": 36409,
      "ad_recallers": 0,
      "spend": 7002.54,
      "cpm": 4.2236,
      "cpc": 0.3101,
      "ctr": 1.3621,
      "frequency": 1.5827,
      "custo_engajamento": 0.0437,
      "custo_link_click": 0.4175,
      "ad_recall_rate": 0.0
    },
    "serie": [
      {
        "impressions": 79921,
        "reach": 76354,
        "clicks": 393,
        "link_clicks": 253,
        "engajamentos": 9032,
        "reacoes": 80,
        "comentarios": 1,
        "salvamentos": 1,
        "compartilhamentos": 2,
        "video_plays": 77387,
        "video_views": 8695,
        "thruplays": 1744,
        "ad_recallers": 0,
        "spend": 248.88,
        "cpm": 3.1141,
        "cpc": 0.6333,
        "ctr": 0.4917,
        "frequency": 1.0467,
        "custo_engajamento": 0.0276,
        "custo_link_click": 0.9837,
        "ad_recall_rate": 0.0,
        "data": "2026-06-17"
      },
      {
        "impressions": 72110,
        "reach": 63974,
        "clicks": 305,
        "link_clicks": 154,
        "engajamentos": 7906,
        "reacoes": 68,
        "comentarios": 3,
        "salvamentos": 0,
        "compartilhamentos": 1,
        "video_plays": 70112,
        "video_views": 7680,
        "thruplays": 1543,
        "ad_recallers": 0,
        "spend": 257.38,
        "cpm": 3.5693,
        "cpc": 0.8439,
        "ctr": 0.423,
        "frequency": 1.1272,
        "custo_engajamento": 0.0326,
        "custo_link_click": 1.6713,
        "ad_recall_rate": 0.0,
        "data": "2026-06-18"
      },
      {
        "impressions": 61260,
        "reach": 61260,
        "clicks": 392,
        "link_clicks": 288,
        "engajamentos": 5654,
        "reacoes": 164,
        "comentarios": 7,
        "salvamentos": 1,
        "compartilhamentos": 0,
        "video_plays": 40223,
        "video_views": 5194,
        "thruplays": 1206,
        "ad_recallers": 0,
        "spend": 198.4,
        "cpm": 3.2387,
        "cpc": 0.5061,
        "ctr": 0.6399,
        "frequency": 1.0,
        "custo_engajamento": 0.0351,
        "custo_link_click": 0.6889,
        "ad_recall_rate": 0.0,
        "data": "2026-06-22"
      },
      {
        "impressions": 148393,
        "reach": 138647,
        "clicks": 1115,
        "link_clicks": 668,
        "engajamentos": 17812,
        "reacoes": 592,
        "comentarios": 23,
        "salvamentos": 7,
        "compartilhamentos": 18,
        "video_plays": 114531,
        "video_views": 16504,
        "thruplays": 4556,
        "ad_recallers": 0,
        "spend": 574.79,
        "cpm": 3.8734,
        "cpc": 0.5155,
        "ctr": 0.7514,
        "frequency": 1.0703,
        "custo_engajamento": 0.0323,
        "custo_link_click": 0.8605,
        "ad_recall_rate": 0.0,
        "data": "2026-06-23"
      },
      {
        "impressions": 243076,
        "reach": 228030,
        "clicks": 1985,
        "link_clicks": 1190,
        "engajamentos": 30394,
        "reacoes": 1159,
        "comentarios": 27,
        "salvamentos": 12,
        "compartilhamentos": 20,
        "video_plays": 179256,
        "video_views": 27986,
        "thruplays": 8025,
        "ad_recallers": 0,
        "spend": 1020.93,
        "cpm": 4.2,
        "cpc": 0.5143,
        "ctr": 0.8166,
        "frequency": 1.066,
        "custo_engajamento": 0.0336,
        "custo_link_click": 0.8579,
        "ad_recall_rate": 0.0,
        "data": "2026-06-24"
      },
      {
        "impressions": 276870,
        "reach": 257059,
        "clicks": 3643,
        "link_clicks": 2579,
        "engajamentos": 27319,
        "reacoes": 1383,
        "comentarios": 45,
        "salvamentos": 9,
        "compartilhamentos": 26,
        "video_plays": 162402,
        "video_views": 23277,
        "thruplays": 6915,
        "ad_recallers": 0,
        "spend": 1196.49,
        "cpm": 4.3215,
        "cpc": 0.3284,
        "ctr": 1.3158,
        "frequency": 1.0771,
        "custo_engajamento": 0.0438,
        "custo_link_click": 0.4639,
        "ad_recall_rate": 0.0,
        "data": "2026-06-25"
      },
      {
        "impressions": 181844,
        "reach": 170637,
        "clicks": 3323,
        "link_clicks": 2648,
        "engajamentos": 13551,
        "reacoes": 777,
        "comentarios": 22,
        "salvamentos": 2,
        "compartilhamentos": 14,
        "video_plays": 77846,
        "video_views": 10088,
        "thruplays": 2631,
        "ad_recallers": 0,
        "spend": 798.48,
        "cpm": 4.391,
        "cpc": 0.2403,
        "ctr": 1.8274,
        "frequency": 1.0657,
        "custo_engajamento": 0.0589,
        "custo_link_click": 0.3015,
        "ad_recall_rate": 0.0,
        "data": "2026-06-26"
      },
      {
        "impressions": 226366,
        "reach": 201991,
        "clicks": 4187,
        "link_clicks": 3317,
        "engajamentos": 19614,
        "reacoes": 1055,
        "comentarios": 22,
        "salvamentos": 1,
        "compartilhamentos": 30,
        "video_plays": 103412,
        "video_views": 15189,
        "thruplays": 3972,
        "ad_recallers": 0,
        "spend": 1065.2,
        "cpm": 4.7057,
        "cpc": 0.2544,
        "ctr": 1.8497,
        "frequency": 1.1207,
        "custo_engajamento": 0.0543,
        "custo_link_click": 0.3211,
        "ad_recall_rate": 0.0,
        "data": "2026-06-27"
      },
      {
        "impressions": 250976,
        "reach": 224675,
        "clicks": 5062,
        "link_clicks": 4012,
        "engajamentos": 19806,
        "reacoes": 1071,
        "comentarios": 25,
        "salvamentos": 4,
        "compartilhamentos": 22,
        "video_plays": 100839,
        "video_views": 14672,
        "thruplays": 4010,
        "ad_recallers": 0,
        "spend": 1122.29,
        "cpm": 4.4717,
        "cpc": 0.2217,
        "ctr": 2.0169,
        "frequency": 1.1171,
        "custo_engajamento": 0.0567,
        "custo_link_click": 0.2797,
        "ad_recall_rate": 0.0,
        "data": "2026-06-28"
      },
      {
        "impressions": 117120,
        "reach": 110042,
        "clicks": 2178,
        "link_clicks": 1664,
        "engajamentos": 9226,
        "reacoes": 536,
        "comentarios": 15,
        "salvamentos": 8,
        "compartilhamentos": 11,
        "video_plays": 47324,
        "video_views": 6992,
        "thruplays": 1807,
        "ad_recallers": 0,
        "spend": 519.7,
        "cpm": 4.4373,
        "cpc": 0.2386,
        "ctr": 1.8596,
        "frequency": 1.0643,
        "custo_engajamento": 0.0563,
        "custo_link_click": 0.3123,
        "ad_recall_rate": 0.0,
        "data": "2026-06-29"
      }
    ],
    "campanhas": {
      "ativas": 32,
      "total": 90,
      "objetivos": [
        "Engajamento",
        "Tráfego",
        "Reconhecimento",
        "LINK_CLICKS",
        "POST_ENGAGEMENT"
      ]
    }
  }
}